PythonConfluenceAPI/__init__.py
PythonConfluenceAPI/api.py
PythonConfluenceAPI/cfapi.py
PythonConfluenceAPI-0.0.1rc4.data/scripts/ez_setup.py
PythonConfluenceAPI-0.0.1rc4.data/scripts/setup.py
PythonConfluenceAPI-0.0.1rc4.dist-info/top_level.txt
PythonConfluenceAPI-0.0.1rc4.dist-info/METADATA
PythonConfluenceAPI-0.0.1rc4.dist-info/DESCRIPTION.rst
PythonConfluenceAPI-0.0.1rc4.dist-info/metadata.json
PythonConfluenceAPI-0.0.1rc4.dist-info/WHEEL
PythonConfluenceAPI-0.0.1rc4.dist-info/RECORD
