Metadata-Version: 2.0
Name: PythonConfluenceAPI
Version: 0.0.1rc4
Summary: PythonConfluenceAPI is a Pythonic API wrapper over the Confluence REST API, which cleanly wraps all of the methods present in the current Confluence API spec, and is easily adapter to be used with minimal effort in other frameworks such as concurrent futures, greenlets, and other concurrency schemes.
Home-page: https://github.com/pushrodtechnology/PythonConfluenceAPI
Author: ('Robert Cope', 'Pushrod Technology')
Author-email: robert.cope@pushrodtechnology.com
License: LGPLv3
Keywords: atlassian confluence api
Platform: UNKNOWN
Classifier: Development Status :: 2 - Pre-Alpha
Classifier: Environment :: Other Environment
Classifier: License :: OSI Approved :: GNU Lesser General Public License v2 or later (LGPLv2+)
Classifier: Operating System :: OS Independent
Classifier: Intended Audience :: Developers
Classifier: Intended Audience :: System Administrators
Classifier: Topic :: Internet :: WWW/HTTP
Classifier: Topic :: Software Development :: Libraries :: Python Modules
Requires-Dist: requests (>=2.3.0)
Requires-Dist: anyjson
Requires-Dist: futures
Requires-Dist: requests-futures
